[
  {
    "name": "Pizza IT",
    "category": "Pizza",
    "availability": true,
    "weight": 450,
    "price": 35,
    "ingredients": [
      "salam",
      "mozzarela",
      "sos de rosii",
      "ciuperci"
    ],
    "img": "pizaQS",
    "id": "rarww1664810866176"
  },
  {
    "id": "c55ebp1664811024442",
    "name": " TEST PIZZA",
    "category": "Pizza",
    "availability": true,
    "weight": 450,
    "price": 35,
    "ingredients": [
      "salam",
      "mozzarela",
      "sos de rosii",
      "ciuperci"
    ],
    "img": "pizaQS"
  },
  {
    "id": "gub14g1664821750996",
    "name": "test retete",
    "category": "Pizza",
    "availability": true,
    "weight": 450,
    "price": 35,
    "ingredients": [
      "salam",
      "mozzarela",
      "sos de rosii",
      "ciuperci"
    ],
    "img": "pizaQS"
  }
]